crossplane/__init__.py
crossplane/__main__.py
crossplane/analyzer.py
crossplane/builder.py
crossplane/compat.py
crossplane/errors.py
crossplane/formatter.py
crossplane/lexer.py
crossplane/parser.py
crossplane/ext/__init__.py
crossplane/ext/abstract.py
crossplane/ext/lua.py
nginx_crossplane-0.5.14.dist-info/licenses/AUTHORS.rst
nginx_crossplane-0.5.14.dist-info/licenses/LICENSE
nginx_crossplane-0.5.14.dist-info/licenses/NOTICE
nginx_crossplane-0.5.14.dist-info/METADATA
nginx_crossplane-0.5.14.dist-info/WHEEL
nginx_crossplane-0.5.14.dist-info/entry_points.txt
nginx_crossplane-0.5.14.dist-info/top_level.txt
nginx_crossplane-0.5.14.dist-info/RECORD
